[
	{
	    "id": 16,
		"img": "img/index_img/1471375816432837124.jpg",
		"price":"￥188.00",
		"del_price":"￥188.00",
		"buy":"立即抢购"
	},
	{
	    "id": 17,
		"img": "img/index_img/1471375812752255638.jpg",
		"price":"￥99.00",
		"del_price":"￥308.00",
		"buy":"立即抢购"
	},{
	    "id": 18,
		"img": "img/index_img/1471375810213443189.jpg",
		"price":"￥138.00",
		"del_price":"￥258.00",
		"buy":"立即抢购"
	},{
	    "id": 19,
		"img": "img/index_img/1023187_thumb_G_1425527106892.jpg",
		"price":"￥668.00",
		"del_price":"￥1328.00",
		"buy":"立即抢购"
	},{
	    "id": 20,
		"img": "img/index_img/1470771030381998808.jpg",
		"price":"￥278.00",
		"del_price":"￥278.00",
		"buy":"立即抢购"
	}
]